strands_mcp_server/__init__.py
strands_mcp_server/__main__.py
strands_mcp_server/config.py
strands_mcp_server/server.py
strands_mcp_server/utils/__init__.py
strands_mcp_server/utils/cache.py
strands_mcp_server/utils/doc_fetcher.py
strands_mcp_server/utils/indexer.py
strands_mcp_server/utils/text_processor.py
strands_agents_mcp_server-0.2.3.dist-info/METADATA
strands_agents_mcp_server-0.2.3.dist-info/WHEEL
strands_agents_mcp_server-0.2.3.dist-info/entry_points.txt
strands_agents_mcp_server-0.2.3.dist-info/licenses/LICENSE
strands_agents_mcp_server-0.2.3.dist-info/licenses/NOTICE
strands_agents_mcp_server-0.2.3.dist-info/RECORD
