Metadata-Version: 2.4
Name: strands-agents-mcp-server
Version: 0.2.3
Summary: A Model Context Protocol server that provides knowledge about building AI agents with Strands Agents
Project-URL: Homepage, https://github.com/strands-agents/mcp-server
Project-URL: Bug Tracker, https://github.com/strands-agents/mcp-server
Project-URL: Documentation, https://strandsagents.com
Author-email: AWS <opensource@amazon.com>
License: Apache-2.0
License-File: LICENSE
License-File: NOTICE
Classifier: Development Status :: 4 - Beta
Classifier: Intended Audience :: Developers
Classifier: License :: OSI Approved :: Apache Software License
Classifier: Operating System :: OS Independent
Classifier: Programming Language :: Python :: 3
Classifier: Programming Language :: Python :: 3.10
Classifier: Programming Language :: Python :: 3.11
Classifier: Programming Language :: Python :: 3.12
Classifier: Programming Language :: Python :: 3.13
Classifier: Topic :: Scientific/Engineering :: Artificial Intelligence
Classifier: Topic :: Software Development :: Libraries :: Python Modules
Requires-Python: >=3.10
Requires-Dist: mcp>=1.1.3
Requires-Dist: pydantic>=2.0.0
Provides-Extra: dev
Requires-Dist: commitizen>=4.4.0; extra == 'dev'
Requires-Dist: hatch>=1.0.0; extra == 'dev'
Requires-Dist: pre-commit>=2.20.0; extra == 'dev'
Requires-Dist: ruff>=0.4.4; extra == 'dev'
